{
  "nurseryRequirements": {"Organique": 20, "Minéral": 35},
  "nurseryDurationMinutes": 1,
  "slotsByLevel": {"1": 1, "2": 2, "3": 3},
  "moduleSlotsByLevel": {"1": 1, "2": 2, "3": 3},
  "productionCycleMinutes": 60,
  "carryingCapacity": 10,
  "nurseryReserveCapacity": 12,
  "sourcierResearchPatternPrice": 7,
  "sourcierSpecializedCellPrice": 4,
  "sourcierNeutralCellPrice": 5,
  "sourcierModulePrice": 6,
  "sourcierCapsulePrice": 10,
  "xpPerCycle": 1,
  "wingsCycleReduction": 0.15,
  "clawProductionBonus": 1,
  "reservoirCapacityBonus": 4,
  "species": {
    "scarabe": {
      "displayName": "Scarabé",
      "styles": ["compact", "cornu", "cuirassé"],
      "creationCost": {"Organique": 30, "Minéral": 15},
      "creationEnergyCost": 0,
      "creationBioBatteryCost": 10,
      "futureMyceliumCost": 0,
      "creationMinutes": 20
    },
    "hyme": {
      "displayName": "Hymé",
      "styles": ["fourmi", "abeille", "guêpe"],
      "creationCost": {"Organique": 30, "Minéral": 15},
      "creationEnergyCost": 0,
      "creationBioBatteryCost": 10,
      "futureMyceliumCost": 0,
      "creationMinutes": 20
    },
    "arac": {
      "displayName": "Arac",
      "styles": ["toile", "chasseuse", "sauteuse"],
      "creationCost": {"Organique": 30, "Minéral": 15},
      "creationEnergyCost": 0,
      "creationBioBatteryCost": 10,
      "futureMyceliumCost": 0,
      "creationMinutes": 25
    }
  },
  "patterns": {
    "scarabe": {
      "kernelPlanId": "ptibug-pattern-scarabe",
      "description": "Un premier collecteur robuste pour les sols du refuge."
    },
    "hyme": {
      "kernelPlanId": "ptibug-pattern-hyme",
      "description": "Un P’TIBUG rapide, adapté aux ressources organiques."
    },
    "arac": {
      "kernelPlanId": "ptibug-pattern-arac",
      "description": "Un collecteur agile capable de s’adapter à sa collecte."
    }
  },
  "sourcierPatternPrices": {"hyme": 6, "arac": 8},
  "traitDefinitions": {
    "pollinisateur": {"id": "pollinisateur", "displayName": "Pollinisateur", "description": "Améliore la collecte organique.", "effects": {"Organique": 1}, "gradeMultipliers": {"commun": 1, "rare": 2, "avance": 3}, "colorHex": "#5D8D71", "isActive": true, "maxLevel": 3, "dataCostByLevel": {"1": {"comportementInsectoide": 3, "organique": 2}, "2": {"comportementInsectoide": 6, "organique": 4, "biomimetisme": 2}, "3": {"comportementInsectoide": 10, "organique": 7, "biomimetisme": 4}}, "materialCostByLevel": {"1": {"Organique": 4, "Minéral": 2}, "2": {"Organique": 7, "Minéral": 4}, "3": {"Organique": 10, "Minéral": 7}}, "energyCostByLevel": {"1": 2, "2": 4, "3": 6}},
    "mineur": {"id": "mineur", "displayName": "Mineur", "description": "Améliore la collecte minérale.", "effects": {"Minéral": 1}, "gradeMultipliers": {"commun": 1, "rare": 2, "avance": 3}, "colorHex": "#4977A6", "isActive": true, "maxLevel": 3, "dataCostByLevel": {"1": {"minerale": 3, "comportementInsectoide": 2}, "2": {"minerale": 6, "biomimetisme": 3, "comportementInsectoide": 2}, "3": {"minerale": 10, "biomimetisme": 6, "comportementInsectoide": 4}}, "materialCostByLevel": {"1": {"Organique": 2, "Minéral": 4}, "2": {"Organique": 4, "Minéral": 7}, "3": {"Organique": 7, "Minéral": 10}}, "energyCostByLevel": {"1": 2, "2": 4, "3": 6}},
    "decomposeur": {"id": "decomposeur", "displayName": "Décomposeur", "description": "Transforme les matières en organique et mycélium.", "effects": {"Organique": 1, "Mycélium": 1}, "gradeMultipliers": {"commun": 1, "rare": 2, "avance": 3}, "colorHex": "#8C5AA2", "isActive": true, "maxLevel": 3, "dataCostByLevel": {"1": {"mycelienne": 3, "organique": 2}, "2": {"mycelienne": 6, "toxine": 3, "organique": 2}, "3": {"mycelienne": 10, "toxine": 6, "organique": 4}}, "materialCostByLevel": {"1": {"Organique": 4, "Minéral": 2}, "2": {"Organique": 7, "Minéral": 4}, "3": {"Organique": 10, "Minéral": 7}}, "energyCostByLevel": {"1": 2, "2": 4, "3": 6}},
    "recuperateur": {"id": "recuperateur", "displayName": "Récupérateur", "description": "Récupère des déchets utiles.", "effects": {"Déchets": 1}, "gradeMultipliers": {"commun": 1, "rare": 2, "avance": 3}, "colorHex": "#8B775A", "isActive": true, "maxLevel": 3, "dataCostByLevel": {"1": {"comportementInsectoide": 3, "minerale": 2}, "2": {"comportementInsectoide": 6, "minerale": 4}, "3": {"comportementInsectoide": 10, "minerale": 7}}, "materialCostByLevel": {"1": {"Organique": 3, "Minéral": 3}, "2": {"Organique": 5, "Minéral": 5}, "3": {"Organique": 8, "Minéral": 8}}, "energyCostByLevel": {"1": 2, "2": 4, "3": 6}},
    "eclaireur": {"id": "eclaireur", "displayName": "Éclaireur", "description": "Augmente la chance de Cellule de données.", "effects": {"Chance Cellule": 5}, "gradeMultipliers": {"commun": 1, "rare": 2, "avance": 3}, "colorHex": "#D29B4B", "isActive": true, "maxLevel": 3, "dataCostByLevel": {"1": {"comportementInsectoide": 3, "energie": 2}, "2": {"comportementInsectoide": 6, "energie": 4}, "3": {"comportementInsectoide": 10, "energie": 7}}, "materialCostByLevel": {"1": {"Organique": 3, "Minéral": 3}, "2": {"Organique": 5, "Minéral": 5}, "3": {"Organique": 8, "Minéral": 8}}, "energyCostByLevel": {"1": 2, "2": 4, "3": 6}},
    "filtreur": {"id": "filtreur", "displayName": "Filtreur", "description": "Favorise les données Toxine.", "effects": {"Poids Toxine": 5}, "gradeMultipliers": {"commun": 1, "rare": 2, "avance": 3}, "colorHex": "#5C9D9A", "isActive": true, "maxLevel": 3, "dataCostByLevel": {"1": {"toxine": 3, "mycelienne": 2}, "2": {"toxine": 6, "mycelienne": 4}, "3": {"toxine": 10, "mycelienne": 7}}, "materialCostByLevel": {"1": {"Organique": 3, "Minéral": 3}, "2": {"Organique": 5, "Minéral": 5}, "3": {"Organique": 8, "Minéral": 8}}, "energyCostByLevel": {"1": 2, "2": 4, "3": 6}},
    "econome": {"id": "econome", "displayName": "Économe", "description": "Réduit les coûts énergétiques.", "effects": {"Réduction énergie": 1}, "gradeMultipliers": {"commun": 1, "rare": 2, "avance": 3}, "colorHex": "#79965B", "isActive": true, "maxLevel": 3, "dataCostByLevel": {"1": {"energie": 3, "biomimetisme": 2}, "2": {"energie": 6, "biomimetisme": 4}, "3": {"energie": 10, "biomimetisme": 7}}, "materialCostByLevel": {"1": {"Organique": 3, "Minéral": 3}, "2": {"Organique": 5, "Minéral": 5}, "3": {"Organique": 8, "Minéral": 8}}, "energyCostByLevel": {"1": 2, "2": 4, "3": 6}},
    "stabilisateur": {"id": "stabilisateur", "displayName": "Stabilisateur", "description": "Entretient légèrement la sécurité locale.", "effects": {"Sécurité locale": 1}, "gradeMultipliers": {"commun": 1, "rare": 2, "avance": 3}, "colorHex": "#6385A4", "isActive": true, "maxLevel": 3, "dataCostByLevel": {"1": {"minerale": 3, "biomimetisme": 2}, "2": {"minerale": 6, "biomimetisme": 4}, "3": {"minerale": 10, "biomimetisme": 7}}, "materialCostByLevel": {"1": {"Organique": 3, "Minéral": 3}, "2": {"Organique": 5, "Minéral": 5}, "3": {"Organique": 8, "Minéral": 8}}, "energyCostByLevel": {"1": 2, "2": 4, "3": 6}}
  },
  "dataQualityValues": {"common": 1, "sought": 2, "rare": 4},
  "dataQualityWeights": {"common": 70, "sought": 25, "rare": 5},
  "moduleCraftCosts": {"ailes": {"Organique": 8, "Minéral": 5}, "pinces": {"Organique": 5, "Minéral": 8}, "reservoir": {"Organique": 10, "Minéral": 10}},
  "moduleCraftEnergyCosts": {"ailes": 2, "pinces": 2, "reservoir": 3},
  "moduleCraftMinutes": {"ailes": 15, "pinces": 15, "reservoir": 20},
  "researchPatterns": {
    "ptibug-species-scarabe": {"id": "ptibug-species-scarabe", "displayName": "Pattern Scarabé", "category": "species", "description": "Un collecteur robuste pour les sols minéraux.", "masteryCosts": {"1": {"minerale": 4, "comportementInsectoide": 3}, "2": {"minerale": 9, "comportementInsectoide": 7, "biomimetisme": 3}, "3": {"minerale": 16, "comportementInsectoide": 13, "biomimetisme": 8}}, "linkedSpecies": "scarabe", "origin": "Kernel", "biomesSuggested": ["hautsRefuges", "semiDesertGarrigueTropicale"]},
    "ptibug-species-hyme": {"id": "ptibug-species-hyme", "displayName": "Pattern Hyme", "category": "species", "description": "Une espèce attentive aux matières organiques.", "masteryCosts": {"1": {"organique": 5, "comportementInsectoide": 4}, "2": {"organique": 10, "comportementInsectoide": 9, "biomimetisme": 3}, "3": {"organique": 18, "comportementInsectoide": 16, "biomimetisme": 8}}, "linkedSpecies": "hyme", "origin": "Sourcier", "biomesSuggested": ["foretHumideRelictuelle", "savaneTropicale"]},
    "ptibug-species-arac": {"id": "ptibug-species-arac", "displayName": "Pattern Arac", "category": "species", "description": "Une espèce polyvalente, sensible à son biome.", "masteryCosts": {"1": {"biomimetisme": 5, "comportementInsectoide": 4}, "2": {"biomimetisme": 11, "comportementInsectoide": 9, "energie": 3}, "3": {"biomimetisme": 20, "comportementInsectoide": 16, "energie": 8}}, "linkedSpecies": "arac", "origin": "Sourcier", "biomesSuggested": ["littoral", "maraisSales"]},
    "ptibug-trait-pollinisateur": {"id": "ptibug-trait-pollinisateur", "displayName": "Pattern Pollinisateur", "category": "trait", "description": "Une spécialisation organique.", "masteryCosts": {"1": {"comportementInsectoide": 6, "organique": 4}, "2": {"comportementInsectoide": 14, "organique": 8, "biomimetisme": 3}, "3": {"comportementInsectoide": 25, "organique": 15, "biomimetisme": 10}}, "linkedTraitId": "pollinisateur", "origin": "Sourcier", "biomesSuggested": ["foretHumideRelictuelle", "savaneTropicale"]},
    "ptibug-trait-mineur": {"id": "ptibug-trait-mineur", "displayName": "Pattern Mineur", "category": "trait", "description": "Une spécialisation minérale.", "masteryCosts": {"1": {"comportementInsectoide": 6, "minerale": 4}, "2": {"comportementInsectoide": 14, "minerale": 8, "biomimetisme": 3}, "3": {"comportementInsectoide": 25, "minerale": 15, "biomimetisme": 10}}, "linkedTraitId": "mineur", "origin": "Sourcier", "biomesSuggested": ["hautsRefuges", "semiDesertGarrigueTropicale"]}
    ,"ptibug-trait-decomposeur": {"id": "ptibug-trait-decomposeur", "displayName": "Pattern Décomposeur", "category": "trait", "description": "Une spécialisation mycélienne et organique.", "masteryCosts": {"1": {"mycelienne": 6, "organique": 4}, "2": {"mycelienne": 14, "toxine": 8, "organique": 3}, "3": {"mycelienne": 25, "toxine": 15, "organique": 10}}, "linkedTraitId": "decomposeur", "origin": "Sourcier", "biomesSuggested": ["foretHumideRelictuelle", "mangroves"]},
    "ptibug-trait-recuperateur": {"id": "ptibug-trait-recuperateur", "displayName": "Pattern Récupérateur", "category": "trait", "description": "Une spécialisation des matériaux délaissés.", "masteryCosts": {"1": {"comportementInsectoide": 6, "minerale": 4}, "2": {"comportementInsectoide": 14, "minerale": 8, "biomimetisme": 3}, "3": {"comportementInsectoide": 25, "minerale": 15, "biomimetisme": 10}}, "linkedTraitId": "recuperateur", "origin": "Sourcier", "biomesSuggested": ["maraisSales", "littoral"]},
    "ptibug-trait-eclaireur": {"id": "ptibug-trait-eclaireur", "displayName": "Pattern Éclaireur", "category": "trait", "description": "Une spécialisation de découverte.", "masteryCosts": {"1": {"comportementInsectoide": 6, "energie": 4}, "2": {"comportementInsectoide": 14, "energie": 8, "biomimetisme": 3}, "3": {"comportementInsectoide": 25, "energie": 15, "biomimetisme": 10}}, "linkedTraitId": "eclaireur", "origin": "Sourcier", "biomesSuggested": ["savaneTropicale", "littoral"]},
    "ptibug-trait-filtreur": {"id": "ptibug-trait-filtreur", "displayName": "Pattern Filtreur", "category": "trait", "description": "Une spécialisation des milieux chargés.", "masteryCosts": {"1": {"toxine": 6, "mycelienne": 4}, "2": {"toxine": 14, "mycelienne": 8, "biomimetisme": 3}, "3": {"toxine": 25, "mycelienne": 15, "biomimetisme": 10}}, "linkedTraitId": "filtreur", "origin": "Sourcier", "biomesSuggested": ["mangroves", "maraisSales"]},
    "ptibug-trait-econome": {"id": "ptibug-trait-econome", "displayName": "Pattern Économe", "category": "trait", "description": "Une spécialisation d'économie d'énergie.", "masteryCosts": {"1": {"energie": 6, "biomimetisme": 4}, "2": {"energie": 14, "biomimetisme": 8, "comportementInsectoide": 3}, "3": {"energie": 25, "biomimetisme": 15, "comportementInsectoide": 10}}, "linkedTraitId": "econome", "origin": "Sourcier", "biomesSuggested": ["foretSecheTropicale", "semiDesertGarrigueTropicale"]},
    "ptibug-trait-stabilisateur": {"id": "ptibug-trait-stabilisateur", "displayName": "Pattern Stabilisateur", "category": "trait", "description": "Une spécialisation de sécurité locale.", "masteryCosts": {"1": {"minerale": 6, "biomimetisme": 4}, "2": {"minerale": 14, "biomimetisme": 8, "energie": 3}, "3": {"minerale": 25, "biomimetisme": 15, "energie": 10}}, "linkedTraitId": "stabilisateur", "origin": "Sourcier", "biomesSuggested": ["hautsRefuges", "maraisSales"]},
    "ptibug-module-ailes": {"id": "ptibug-module-ailes", "displayName": "Pattern Ailes", "category": "module", "description": "Un module qui réduit le temps de cycle.", "masteryCosts": {"1": {"biomimetisme": 4, "minerale": 3}, "2": {"biomimetisme": 9, "minerale": 7, "energie": 2}, "3": {"biomimetisme": 16, "minerale": 12, "energie": 6}}, "linkedModuleType": "ailes", "origin": "Sourcier", "biomesSuggested": ["savaneTropicale", "littoral"]},
    "ptibug-module-pinces": {"id": "ptibug-module-pinces", "displayName": "Pattern Pinces", "category": "module", "description": "Un module qui augmente la production.", "masteryCosts": {"1": {"minerale": 4, "biomimetisme": 3}, "2": {"minerale": 9, "biomimetisme": 7, "energie": 2}, "3": {"minerale": 16, "biomimetisme": 12, "energie": 6}}, "linkedModuleType": "pinces", "origin": "Sourcier", "biomesSuggested": ["hautsRefuges", "semiDesertGarrigueTropicale"]},
    "ptibug-module-reservoir": {"id": "ptibug-module-reservoir", "displayName": "Pattern Réservoir", "category": "module", "description": "Un module qui augmente fortement la capacité.", "masteryCosts": {"1": {"organique": 4, "biomimetisme": 3}, "2": {"organique": 9, "biomimetisme": 7, "energie": 2}, "3": {"organique": 16, "biomimetisme": 12, "energie": 6}}, "linkedModuleType": "reservoir", "origin": "Sourcier", "biomesSuggested": ["foretHumideRelictuelle", "mangroves"]}
  },
  "biomes": {
    "hautsRefuges": {"displayName": "Hauts-Refuges", "risks": ["Glissements", "Vents", "Anciennes structures"], "dataWeights": {"minerale": 45, "biomimetisme": 30, "energie": 25}, "aracProductionWeights": {"Minéral": 60, "Organique": 20, "Déchets": 20}, "localProductionBonus": {"scarabe": {"Minéral": 1}}, "nurseryInsectBehaviourWeight": 8},
    "foretHumideRelictuelle": {"displayName": "Forêt humide relictuelle", "risks": ["Humidité", "Spores", "Faible visibilité", "Toxines biologiques"], "dataWeights": {"organique": 40, "mycelienne": 35, "biomimetisme": 25}, "aracProductionWeights": {"Organique": 60, "Déchets": 25, "Minéral": 15}, "localProductionBonus": {"hyme": {"Organique": 1}}, "nurseryInsectBehaviourWeight": 8},
    "foretSecheTropicale": {"displayName": "Forêt sèche tropicale", "risks": ["Chaleur", "Sécheresse", "Incendies locaux"], "dataWeights": {"organique": 40, "energie": 35, "biomimetisme": 25}, "aracProductionWeights": {"Organique": 50, "Minéral": 30, "Déchets": 20}, "localProductionBonus": {"hyme": {"Organique": 1}}, "nurseryInsectBehaviourWeight": 8},
    "savaneTropicale": {"displayName": "Savane tropicale", "risks": ["Exposition", "Chaleur", "Déchets anciens", "Petits organismes"], "dataWeights": {"organique": 35, "biomimetisme": 30, "comportementInsectoide": 35}, "aracProductionWeights": {"Organique": 45, "Minéral": 25, "Déchets": 30}, "localProductionBonus": {"hyme": {"Organique": 1}}, "nurseryInsectBehaviourWeight": 12},
    "mangroves": {"displayName": "Mangroves", "risks": ["Sols instables", "Eau stagnante", "Biofilms", "Salinité"], "dataWeights": {"mycelienne": 40, "toxine": 35, "organique": 25}, "aracProductionWeights": {"Organique": 45, "Déchets": 45, "Minéral": 10}, "localProductionBonus": {"hyme": {"Organique": 1}}, "nurseryInsectBehaviourWeight": 10},
    "maraisSales": {"displayName": "Marais salés", "risks": ["Corrosion", "Toxines", "Sol fragile", "Forte salinité"], "dataWeights": {"toxine": 40, "minerale": 35, "energie": 25}, "aracProductionWeights": {"Minéral": 40, "Déchets": 45, "Organique": 15}, "localProductionBonus": {"scarabe": {"Minéral": 1}}, "nurseryInsectBehaviourWeight": 8},
    "semiDesertGarrigueTropicale": {"displayName": "Semi-désert / Garrigue tropicale", "risks": ["Chaleur", "Poussières", "Vent", "Manque d’ombre"], "dataWeights": {"minerale": 45, "energie": 30, "biomimetisme": 25}, "aracProductionWeights": {"Minéral": 55, "Déchets": 30, "Organique": 15}, "localProductionBonus": {"scarabe": {"Minéral": 1}}, "nurseryInsectBehaviourWeight": 8},
    "littoral": {"displayName": "Littoral", "risks": ["Corrosion", "Embruns", "Vents", "Ruissellement", "Structures marines"], "dataWeights": {"energie": 40, "toxine": 30, "minerale": 30}, "aracProductionWeights": {"Minéral": 40, "Déchets": 45, "Organique": 15}, "localProductionBonus": {}, "nurseryInsectBehaviourWeight": 8}
  }
}
